<?xml version="1.0" encoding="UTF-8" standalone="no"?>
<databaseChangeLog xmlns="http://www.liquibase.org/xml/ns/dbchangelog/1.9" xmlns:xsi="http://www.w3.org/2001/XMLSchema-instance" xsi:schemaLocation="http://www.liquibase.org/xml/ns/dbchangelog/1.9 http://www.liquibase.org/xml/ns/dbchangelog/dbchangelog-1.9.xsd">
    <changeSet author="Job (generated)" id="1367517581199-1">
        <addNotNullConstraint columnDataType="varchar(255)" columnName="user_id" defaultNullValue="" tableName="committee_member"/>
    </changeSet>
    <changeSet author="Job (generated)" id="1367517581199-2">
        <addNotNullConstraint columnDataType="varchar(1000)" columnName="text" defaultNullValue="" tableName="post"/>
    </changeSet>
    <changeSet author="Job (generated)" id="1367517581199-3">
        <createIndex indexName="key1" tableName="concept_category_link">
            <column name="concept_id"/>
            <column name="concept_category_id"/>
        </createIndex>
    </changeSet>
    <changeSet author="Job (generated)" id="1367517581199-4">
        <createIndex indexName="uk_crop_inputs" tableName="crop_inputs">
            <column name="crop_id"/>
            <column name="concept_id"/>
        </createIndex>
    </changeSet>
    <changeSet author="Job (generated)" id="1367517581199-5">
        <createIndex indexName="uk_inter_cropping_methods" tableName="crop_inter_cropping_types">
            <column name="crop_id"/>
            <column name="concept_id"/>
        </createIndex>
    </changeSet>
    <changeSet author="Job (generated)" id="1367517581199-6">
        <createIndex indexName="uk_crop_ploughing_methods" tableName="crop_ploughing_methods">
            <column name="crop_id"/>
            <column name="concept_id"/>
        </createIndex>
    </changeSet>
    <changeSet author="Job (generated)" id="1367517581199-7">
        <createIndex indexName="uk_crop_seedvirieties" tableName="crop_seed_varieties">
            <column name="crop_id"/>
            <column name="concept_id"/>
        </createIndex>
    </changeSet>
    <changeSet author="Job (generated)" id="1367517581199-8">
        <createIndex indexName="uk_crop_sunitsofmeasure" tableName="crop_units_of_measure">
            <column name="crop_id"/>
            <column name="concept_id"/>
        </createIndex>
    </changeSet>
    <changeSet author="Job (generated)" id="1367517581199-9">
        <createIndex indexName="uk_place_selling_types" tableName="place_selling_types">
            <column name="selling_place_id"/>
            <column name="concept_id"/>
        </createIndex>
    </changeSet>
    <changeSet author="Job (generated)" id="1367517581199-10">
        <createIndex indexName="UKC1E628651E3346BF" tableName="publication_documents">
            <column name="document_id"/>
        </createIndex>
    </changeSet>
    <changeSet author="Job (generated)" id="1367517581199-11">
        <dropIndex indexName="FK38A5EE5F6BA9B6BB" tableName="comment"/>
    </changeSet>
    <changeSet author="Job (generated)" id="1367517581199-12">
        <dropIndex indexName="FKA71EF77D7EF2A060" tableName="committee"/>
    </changeSet>
    <changeSet author="Job (generated)" id="1367517581199-13">
        <dropIndex indexName="FK1792999C5BA33ADC" tableName="committee_member"/>
    </changeSet>
    <changeSet author="Job (generated)" id="1367517581199-14">
        <dropIndex indexName="FK1792999C6BA9B6BB" tableName="committee_member"/>
    </changeSet>
    <changeSet author="Job (generated)" id="1367517581199-15">
        <dropIndex indexName="key1" tableName="concept_category_link"/>
    </changeSet>
    <changeSet author="Job (generated)" id="1367517581199-16">
        <dropIndex indexName="FK7434E27836176439" tableName="crop_inputs"/>
    </changeSet>
    <changeSet author="Job (generated)" id="1367517581199-17">
        <dropIndex indexName="uk_crop_inputs" tableName="crop_inputs"/>
    </changeSet>
    <changeSet author="Job (generated)" id="1367517581199-18">
        <dropIndex indexName="FK68BD760E36176439" tableName="crop_inter_cropping_types"/>
    </changeSet>
    <changeSet author="Job (generated)" id="1367517581199-19">
        <dropIndex indexName="uk_inter_cropping_methods" tableName="crop_inter_cropping_types"/>
    </changeSet>
    <changeSet author="Job (generated)" id="1367517581199-20">
        <dropIndex indexName="FK2F54674336176439" tableName="crop_ploughing_methods"/>
    </changeSet>
    <changeSet author="Job (generated)" id="1367517581199-21">
        <dropIndex indexName="uk_crop_ploughing_methods" tableName="crop_ploughing_methods"/>
    </changeSet>
    <changeSet author="Job (generated)" id="1367517581199-22">
        <dropIndex indexName="FK7915702736176439" tableName="crop_seed_varieties"/>
    </changeSet>
    <changeSet author="Job (generated)" id="1367517581199-23">
        <dropIndex indexName="uk_crop_seedvirieties" tableName="crop_seed_varieties"/>
    </changeSet>
    <changeSet author="Job (generated)" id="1367517581199-24">
        <dropIndex indexName="FK582FF9536176439" tableName="crop_units_of_measure"/>
    </changeSet>
    <changeSet author="Job (generated)" id="1367517581199-25">
        <dropIndex indexName="uk_crop_sunitsofmeasure" tableName="crop_units_of_measure"/>
    </changeSet>
    <changeSet author="Job (generated)" id="1367517581199-26">
        <dropIndex indexName="FK383D52B880255C5" tableName="documents"/>
    </changeSet>
    <changeSet author="Job (generated)" id="1367517581199-27">
        <dropIndex indexName="FK383D52B8C61271BA" tableName="documents"/>
    </changeSet>
    <changeSet author="Job (generated)" id="1367517581199-28">
        <dropIndex indexName="FK383D52B8D0B0822F" tableName="documents"/>
    </changeSet>
    <changeSet author="Job (generated)" id="1367517581199-29">
        <dropIndex indexName="FK3C84CDF86B3B4639" tableName="financial_service_doc"/>
    </changeSet>
    <changeSet author="Job (generated)" id="1367517581199-30">
        <dropIndex indexName="FK9F9E99331AC06994" tableName="land_use"/>
    </changeSet>
    <changeSet author="Job (generated)" id="1367517581199-31">
        <dropIndex indexName="FK9F9E9933B248849B" tableName="land_use"/>
    </changeSet>
    <changeSet author="Job (generated)" id="1367517581199-32">
        <dropIndex indexName="FK38EB0007746ED727" tableName="message"/>
    </changeSet>
    <changeSet author="Job (generated)" id="1367517581199-33">
        <dropIndex indexName="FK38EB0007749EE056" tableName="message"/>
    </changeSet>
    <changeSet author="Job (generated)" id="1367517581199-34">
        <dropIndex indexName="FKC4AB183DEE32605A" tableName="parish"/>
    </changeSet>
    <changeSet author="Job (generated)" id="1367517581199-35">
        <dropIndex indexName="FK6A50819236176439" tableName="place_selling_types"/>
    </changeSet>
    <changeSet author="Job (generated)" id="1367517581199-36">
        <dropIndex indexName="uk_place_selling_types" tableName="place_selling_types"/>
    </changeSet>
    <changeSet author="Job (generated)" id="1367517581199-37">
        <dropIndex indexName="FK3498A076A74627" tableName="post"/>
    </changeSet>
    <changeSet author="Job (generated)" id="1367517581199-38">
        <dropIndex indexName="FK3498A07AC2BB5F" tableName="post"/>
    </changeSet>
    <changeSet author="Job (generated)" id="1367517581199-39">
        <dropIndex indexName="FK3498A0B248849B" tableName="post"/>
    </changeSet>
    <changeSet author="Job (generated)" id="1367517581199-40">
        <dropIndex indexName="FK65FB1491CC91A78" tableName="price"/>
    </changeSet>
    <changeSet author="Job (generated)" id="1367517581199-41">
        <dropIndex indexName="FK65FB14983E010B0" tableName="price"/>
    </changeSet>
    <changeSet author="Job (generated)" id="1367517581199-42">
        <dropIndex indexName="FK65FB149B248849B" tableName="price"/>
    </changeSet>
    <changeSet author="Job (generated)" id="1367517581199-43">
        <dropIndex indexName="FK65FB149D7199ADA" tableName="price"/>
    </changeSet>
    <changeSet author="Job (generated)" id="1367517581199-44">
        <dropIndex indexName="FK23E294B7A1DA35B" tableName="producer_org"/>
    </changeSet>
    <changeSet author="Job (generated)" id="1367517581199-45">
        <dropIndex indexName="FK23E294B7EE32605A" tableName="producer_org"/>
    </changeSet>
    <changeSet author="Job (generated)" id="1367517581199-46">
        <dropIndex indexName="FKC1E628656B3B4639" tableName="publication_documents"/>
    </changeSet>
    <changeSet author="Job (generated)" id="1367517581199-47">
        <dropIndex indexName="FK37B8A3C748408754" tableName="publications"/>
    </changeSet>
    <changeSet author="Job (generated)" id="1367517581199-48">
        <dropIndex indexName="FK37B8A3C796BC074C" tableName="publications"/>
    </changeSet>
    <changeSet author="Job (generated)" id="1367517581199-49">
        <dropIndex indexName="FKEAD9D23BC67EF2DB" tableName="role_permissions"/>
    </changeSet>
    <changeSet author="Job (generated)" id="1367517581199-50">
        <dropIndex indexName="FK6CF7C0FFC67EF2DB" tableName="role_users"/>
    </changeSet>
    <changeSet author="Job (generated)" id="1367517581199-51">
        <dropIndex indexName="FK71572F58A1DA35B" tableName="selling_place"/>
    </changeSet>
    <changeSet author="Job (generated)" id="1367517581199-52">
        <dropIndex indexName="FK5470C8D95BA33ADC" tableName="staff_member"/>
    </changeSet>
    <changeSet author="Job (generated)" id="1367517581199-53">
        <dropIndex indexName="FK5470C8D96BA9B6BB" tableName="staff_member"/>
    </changeSet>
    <changeSet author="Job (generated)" id="1367517581199-54">
        <dropIndex indexName="FK5470C8D97EF2A060" tableName="staff_member"/>
    </changeSet>
    <changeSet author="Job (generated)" id="1367517581199-55">
        <dropIndex indexName="FK952A8829A1DA35B" tableName="sub_county"/>
    </changeSet>
    <changeSet author="Job (generated)" id="1367517581199-56">
        <dropIndex indexName="FK6A68E087EF2A060" tableName="users"/>
    </changeSet>
    <changeSet author="Job (generated)" id="1367517581199-57">
        <dropIndex indexName="FK6A68E088CDA553B" tableName="users"/>
    </changeSet>
    <changeSet author="Job (generated)" id="1367517581199-58">
        <dropIndex indexName="FK6A68E08A1DA35B" tableName="users"/>
    </changeSet>
    <changeSet author="Job (generated)" id="1367517581199-59">
        <dropIndex indexName="FK6A68E08A3C8C159" tableName="users"/>
    </changeSet>
    <changeSet author="Job (generated)" id="1367517581199-60">
        <dropIndex indexName="FK1B70A4AC8CDA553B" tableName="village"/>
    </changeSet>
    <changeSet author="Job (generated)" id="1367517581199-61">
        <addForeignKeyConstraint baseColumnNames="post_id" baseTableName="comment" constraintName="FK38A5EE5F5D1B0A9B" deferrable="false" initiallyDeferred="false" referencedColumnNames="id" referencedTableName="post"/>
    </changeSet>
    <changeSet author="Job (generated)" id="1367517581199-62">
        <addForeignKeyConstraint baseColumnNames="user_id" baseTableName="comment" constraintName="FK38A5EE5F6BA9B6BB" deferrable="false" initiallyDeferred="false" referencedColumnNames="id" referencedTableName="users"/>
    </changeSet>
    <changeSet author="Job (generated)" id="1367517581199-63">
        <addForeignKeyConstraint baseColumnNames="producer_organisation_id" baseTableName="committee" constraintName="FKA71EF77D7EF2A060" deferrable="false" initiallyDeferred="false" referencedColumnNames="id" referencedTableName="producer_org"/>
    </changeSet>
    <changeSet author="Job (generated)" id="1367517581199-64">
        <addForeignKeyConstraint baseColumnNames="committee_id" baseTableName="committee_member" constraintName="FK1792999C3406EC59" deferrable="false" initiallyDeferred="false" referencedColumnNames="id" referencedTableName="committee"/>
    </changeSet>
    <changeSet author="Job (generated)" id="1367517581199-65">
        <addForeignKeyConstraint baseColumnNames="postion_id" baseTableName="committee_member" constraintName="FK1792999C5BA33ADC" deferrable="false" initiallyDeferred="false" referencedColumnNames="id" referencedTableName="position"/>
    </changeSet>
    <changeSet author="Job (generated)" id="1367517581199-66">
        <addForeignKeyConstraint baseColumnNames="user_id" baseTableName="committee_member" constraintName="FK1792999C6BA9B6BB" deferrable="false" initiallyDeferred="false" referencedColumnNames="id" referencedTableName="users"/>
    </changeSet>
    <changeSet author="Job (generated)" id="1367517581199-67">
        <addForeignKeyConstraint baseColumnNames="concept_category_id" baseTableName="concept_category_link" constraintName="FKD1B211043100D8AA" deferrable="false" initiallyDeferred="false" referencedColumnNames="id" referencedTableName="concept_categories"/>
    </changeSet>
    <changeSet author="Job (generated)" id="1367517581199-68">
        <addForeignKeyConstraint baseColumnNames="concept_id" baseTableName="concept_category_link" constraintName="FKD1B2110436176439" deferrable="false" initiallyDeferred="false" referencedColumnNames="id" referencedTableName="concepts"/>
    </changeSet>
    <changeSet author="Job (generated)" id="1367517581199-69">
        <addForeignKeyConstraint baseColumnNames="concept_id" baseTableName="crop_inputs" constraintName="FK7434E27836176439" deferrable="false" initiallyDeferred="false" referencedColumnNames="id" referencedTableName="concepts"/>
    </changeSet>
    <changeSet author="Job (generated)" id="1367517581199-70">
        <addForeignKeyConstraint baseColumnNames="crop_id" baseTableName="crop_inputs" constraintName="FK7434E278B248849B" deferrable="false" initiallyDeferred="false" referencedColumnNames="id" referencedTableName="crop"/>
    </changeSet>
    <changeSet author="Job (generated)" id="1367517581199-71">
        <addForeignKeyConstraint baseColumnNames="concept_id" baseTableName="crop_inter_cropping_types" constraintName="FK68BD760E36176439" deferrable="false" initiallyDeferred="false" referencedColumnNames="id" referencedTableName="concepts"/>
    </changeSet>
    <changeSet author="Job (generated)" id="1367517581199-72">
        <addForeignKeyConstraint baseColumnNames="crop_id" baseTableName="crop_inter_cropping_types" constraintName="FK68BD760EB248849B" deferrable="false" initiallyDeferred="false" referencedColumnNames="id" referencedTableName="crop"/>
    </changeSet>
    <changeSet author="Job (generated)" id="1367517581199-73">
        <addForeignKeyConstraint baseColumnNames="concept_id" baseTableName="crop_ploughing_methods" constraintName="FK2F54674336176439" deferrable="false" initiallyDeferred="false" referencedColumnNames="id" referencedTableName="concepts"/>
    </changeSet>
    <changeSet author="Job (generated)" id="1367517581199-74">
        <addForeignKeyConstraint baseColumnNames="crop_id" baseTableName="crop_ploughing_methods" constraintName="FK2F546743B248849B" deferrable="false" initiallyDeferred="false" referencedColumnNames="id" referencedTableName="crop"/>
    </changeSet>
    <changeSet author="Job (generated)" id="1367517581199-75">
        <addForeignKeyConstraint baseColumnNames="concept_id" baseTableName="crop_seed_varieties" constraintName="FK7915702736176439" deferrable="false" initiallyDeferred="false" referencedColumnNames="id" referencedTableName="concepts"/>
    </changeSet>
    <changeSet author="Job (generated)" id="1367517581199-76">
        <addForeignKeyConstraint baseColumnNames="crop_id" baseTableName="crop_seed_varieties" constraintName="FK79157027B248849B" deferrable="false" initiallyDeferred="false" referencedColumnNames="id" referencedTableName="crop"/>
    </changeSet>
    <changeSet author="Job (generated)" id="1367517581199-77">
        <addForeignKeyConstraint baseColumnNames="concept_id" baseTableName="crop_units_of_measure" constraintName="FK582FF9536176439" deferrable="false" initiallyDeferred="false" referencedColumnNames="id" referencedTableName="concepts"/>
    </changeSet>
    <changeSet author="Job (generated)" id="1367517581199-78">
        <addForeignKeyConstraint baseColumnNames="crop_id" baseTableName="crop_units_of_measure" constraintName="FK582FF95B248849B" deferrable="false" initiallyDeferred="false" referencedColumnNames="id" referencedTableName="crop"/>
    </changeSet>
    <changeSet author="Job (generated)" id="1367517581199-79">
        <addForeignKeyConstraint baseColumnNames="created_by" baseTableName="documents" constraintName="FK383D52B8C61271BA" deferrable="false" initiallyDeferred="false" referencedColumnNames="id" referencedTableName="users"/>
    </changeSet>
    <changeSet author="Job (generated)" id="1367517581199-80">
        <addForeignKeyConstraint baseColumnNames="document_type" baseTableName="documents" constraintName="FK383D52B880255C5" deferrable="false" initiallyDeferred="false" referencedColumnNames="id" referencedTableName="concepts"/>
    </changeSet>
    <changeSet author="Job (generated)" id="1367517581199-81">
        <addForeignKeyConstraint baseColumnNames="user_document_owner" baseTableName="documents" constraintName="FK383D52B8D0B0822F" deferrable="false" initiallyDeferred="false" referencedColumnNames="id" referencedTableName="users"/>
    </changeSet>
    <changeSet author="Job (generated)" id="1367517581199-82">
        <addForeignKeyConstraint baseColumnNames="financial_institutution_id" baseTableName="financial_service_doc" constraintName="FK3C84CDF857444DA7" deferrable="false" initiallyDeferred="false" referencedColumnNames="id" referencedTableName="financial_institution"/>
    </changeSet>
    <changeSet author="Job (generated)" id="1367517581199-83">
        <addForeignKeyConstraint baseColumnNames="publication_id" baseTableName="financial_service_doc" constraintName="FK3C84CDF86B3B4639" deferrable="false" initiallyDeferred="false" referencedColumnNames="id" referencedTableName="publications"/>
    </changeSet>
    <changeSet author="Job (generated)" id="1367517581199-84">
        <addForeignKeyConstraint baseColumnNames="crop_id" baseTableName="land_use" constraintName="FK9F9E9933B248849B" deferrable="false" initiallyDeferred="false" referencedColumnNames="id" referencedTableName="crop"/>
    </changeSet>
    <changeSet author="Job (generated)" id="1367517581199-85">
        <addForeignKeyConstraint baseColumnNames="producer_id" baseTableName="land_use" constraintName="FK9F9E99331AC06994" deferrable="false" initiallyDeferred="false" referencedColumnNames="id" referencedTableName="users"/>
    </changeSet>
    <changeSet author="Job (generated)" id="1367517581199-86">
        <addForeignKeyConstraint baseColumnNames="from" baseTableName="message" constraintName="FK38EB0007749EE056" deferrable="false" initiallyDeferred="false" referencedColumnNames="id" referencedTableName="users"/>
    </changeSet>
    <changeSet author="Job (generated)" id="1367517581199-87">
        <addForeignKeyConstraint baseColumnNames="to" baseTableName="message" constraintName="FK38EB0007746ED727" deferrable="false" initiallyDeferred="false" referencedColumnNames="id" referencedTableName="users"/>
    </changeSet>
    <changeSet author="Job (generated)" id="1367517581199-88">
        <addForeignKeyConstraint baseColumnNames="sub_county_id" baseTableName="parish" constraintName="FKC4AB183DEE32605A" deferrable="false" initiallyDeferred="false" referencedColumnNames="id" referencedTableName="sub_county"/>
    </changeSet>
    <changeSet author="Job (generated)" id="1367517581199-89">
        <addForeignKeyConstraint baseColumnNames="concept_id" baseTableName="place_selling_types" constraintName="FK6A50819236176439" deferrable="false" initiallyDeferred="false" referencedColumnNames="id" referencedTableName="concepts"/>
    </changeSet>
    <changeSet author="Job (generated)" id="1367517581199-90">
        <addForeignKeyConstraint baseColumnNames="selling_place_id" baseTableName="place_selling_types" constraintName="FK6A508192D7199ADA" deferrable="false" initiallyDeferred="false" referencedColumnNames="id" referencedTableName="selling_place"/>
    </changeSet>
    <changeSet author="Job (generated)" id="1367517581199-91">
        <addForeignKeyConstraint baseColumnNames="crop_id" baseTableName="post" constraintName="FK3498A0B248849B" deferrable="false" initiallyDeferred="false" referencedColumnNames="id" referencedTableName="crop"/>
    </changeSet>
    <changeSet author="Job (generated)" id="1367517581199-92">
        <addForeignKeyConstraint baseColumnNames="owner" baseTableName="post" constraintName="FK3498A07AC2BB5F" deferrable="false" initiallyDeferred="false" referencedColumnNames="id" referencedTableName="users"/>
    </changeSet>
    <changeSet author="Job (generated)" id="1367517581199-93">
        <addForeignKeyConstraint baseColumnNames="type_id" baseTableName="post" constraintName="FK3498A076A74627" deferrable="false" initiallyDeferred="false" referencedColumnNames="id" referencedTableName="concepts"/>
    </changeSet>
    <changeSet author="Job (generated)" id="1367517581199-94">
        <addForeignKeyConstraint baseColumnNames="crop_id" baseTableName="price" constraintName="FK65FB149B248849B" deferrable="false" initiallyDeferred="false" referencedColumnNames="id" referencedTableName="crop"/>
    </changeSet>
    <changeSet author="Job (generated)" id="1367517581199-95">
        <addForeignKeyConstraint baseColumnNames="selling_place_id" baseTableName="price" constraintName="FK65FB149D7199ADA" deferrable="false" initiallyDeferred="false" referencedColumnNames="id" referencedTableName="selling_place"/>
    </changeSet>
    <changeSet author="Job (generated)" id="1367517581199-96">
        <addForeignKeyConstraint baseColumnNames="selling_type" baseTableName="price" constraintName="FK65FB14983E010B0" deferrable="false" initiallyDeferred="false" referencedColumnNames="id" referencedTableName="concepts"/>
    </changeSet>
    <changeSet author="Job (generated)" id="1367517581199-97">
        <addForeignKeyConstraint baseColumnNames="unit_of_measure" baseTableName="price" constraintName="FK65FB1491CC91A78" deferrable="false" initiallyDeferred="false" referencedColumnNames="id" referencedTableName="concepts"/>
    </changeSet>
    <changeSet author="Job (generated)" id="1367517581199-98">
        <addForeignKeyConstraint baseColumnNames="district_id" baseTableName="producer_org" constraintName="FK23E294B7A1DA35B" deferrable="false" initiallyDeferred="false" referencedColumnNames="id" referencedTableName="district"/>
    </changeSet>
    <changeSet author="Job (generated)" id="1367517581199-99">
        <addForeignKeyConstraint baseColumnNames="sub_county_id" baseTableName="producer_org" constraintName="FK23E294B7EE32605A" deferrable="false" initiallyDeferred="false" referencedColumnNames="id" referencedTableName="sub_county"/>
    </changeSet>
    <changeSet author="Job (generated)" id="1367517581199-100">
        <addForeignKeyConstraint baseColumnNames="document_id" baseTableName="publication_documents" constraintName="FKC1E62865FADC9C3B" deferrable="false" initiallyDeferred="false" referencedColumnNames="id" referencedTableName="documents"/>
    </changeSet>
    <changeSet author="Job (generated)" id="1367517581199-101">
        <addForeignKeyConstraint baseColumnNames="publication_id" baseTableName="publication_documents" constraintName="FKC1E628656B3B4639" deferrable="false" initiallyDeferred="false" referencedColumnNames="id" referencedTableName="publications"/>
    </changeSet>
    <changeSet author="Job (generated)" id="1367517581199-102">
        <addForeignKeyConstraint baseColumnNames="publication_status" baseTableName="publications" constraintName="FK37B8A3C796BC074C" deferrable="false" initiallyDeferred="false" referencedColumnNames="id" referencedTableName="concepts"/>
    </changeSet>
    <changeSet author="Job (generated)" id="1367517581199-103">
        <addForeignKeyConstraint baseColumnNames="publication_type" baseTableName="publications" constraintName="FK37B8A3C748408754" deferrable="false" initiallyDeferred="false" referencedColumnNames="id" referencedTableName="concepts"/>
    </changeSet>
    <changeSet author="Job (generated)" id="1367517581199-104">
        <addForeignKeyConstraint baseColumnNames="permission_id" baseTableName="role_permissions" constraintName="FKEAD9D23B140A5B7B" deferrable="false" initiallyDeferred="false" referencedColumnNames="id" referencedTableName="permissions"/>
    </changeSet>
    <changeSet author="Job (generated)" id="1367517581199-105">
        <addForeignKeyConstraint baseColumnNames="role_id" baseTableName="role_permissions" constraintName="FKEAD9D23BC67EF2DB" deferrable="false" initiallyDeferred="false" referencedColumnNames="id" referencedTableName="roles"/>
    </changeSet>
    <changeSet author="Job (generated)" id="1367517581199-106">
        <addForeignKeyConstraint baseColumnNames="role_id" baseTableName="role_users" constraintName="FK6CF7C0FFC67EF2DB" deferrable="false" initiallyDeferred="false" referencedColumnNames="id" referencedTableName="roles"/>
    </changeSet>
    <changeSet author="Job (generated)" id="1367517581199-107">
        <addForeignKeyConstraint baseColumnNames="user_id" baseTableName="role_users" constraintName="FK6CF7C0FF6BA9B6BB" deferrable="false" initiallyDeferred="false" referencedColumnNames="id" referencedTableName="users"/>
    </changeSet>
    <changeSet author="Job (generated)" id="1367517581199-108">
        <addForeignKeyConstraint baseColumnNames="district_id" baseTableName="selling_place" constraintName="FK71572F58A1DA35B" deferrable="false" initiallyDeferred="false" referencedColumnNames="id" referencedTableName="district"/>
    </changeSet>
    <changeSet author="Job (generated)" id="1367517581199-109">
        <addForeignKeyConstraint baseColumnNames="postion_id" baseTableName="staff_member" constraintName="FK5470C8D95BA33ADC" deferrable="false" initiallyDeferred="false" referencedColumnNames="id" referencedTableName="position"/>
    </changeSet>
    <changeSet author="Job (generated)" id="1367517581199-110">
        <addForeignKeyConstraint baseColumnNames="producer_organisation_id" baseTableName="staff_member" constraintName="FK5470C8D97EF2A060" deferrable="false" initiallyDeferred="false" referencedColumnNames="id" referencedTableName="producer_org"/>
    </changeSet>
    <changeSet author="Job (generated)" id="1367517581199-111">
        <addForeignKeyConstraint baseColumnNames="user_id" baseTableName="staff_member" constraintName="FK5470C8D96BA9B6BB" deferrable="false" initiallyDeferred="false" referencedColumnNames="id" referencedTableName="users"/>
    </changeSet>
    <changeSet author="Job (generated)" id="1367517581199-112">
        <addForeignKeyConstraint baseColumnNames="district_id" baseTableName="sub_county" constraintName="FK952A8829A1DA35B" deferrable="false" initiallyDeferred="false" referencedColumnNames="id" referencedTableName="district"/>
    </changeSet>
    <changeSet author="Job (generated)" id="1367517581199-113">
        <addForeignKeyConstraint baseColumnNames="district_id" baseTableName="users" constraintName="FK6A68E08A1DA35B" deferrable="false" initiallyDeferred="false" referencedColumnNames="id" referencedTableName="district"/>
    </changeSet>
    <changeSet author="Job (generated)" id="1367517581199-114">
        <addForeignKeyConstraint baseColumnNames="gis_cordinates_id" baseTableName="users" constraintName="FK6A68E082AC304E7" deferrable="false" initiallyDeferred="false" referencedColumnNames="id" referencedTableName="gis_cordinate"/>
    </changeSet>
    <changeSet author="Job (generated)" id="1367517581199-115">
        <addForeignKeyConstraint baseColumnNames="parish_id" baseTableName="users" constraintName="FK6A68E088CDA553B" deferrable="false" initiallyDeferred="false" referencedColumnNames="id" referencedTableName="parish"/>
    </changeSet>
    <changeSet author="Job (generated)" id="1367517581199-116">
        <addForeignKeyConstraint baseColumnNames="producer_organisation_id" baseTableName="users" constraintName="FK6A68E087EF2A060" deferrable="false" initiallyDeferred="false" referencedColumnNames="id" referencedTableName="producer_org"/>
    </changeSet>
    <changeSet author="Job (generated)" id="1367517581199-117">
        <addForeignKeyConstraint baseColumnNames="subcounty_id" baseTableName="users" constraintName="FK6A68E08A3C8C159" deferrable="false" initiallyDeferred="false" referencedColumnNames="id" referencedTableName="sub_county"/>
    </changeSet>
    <changeSet author="Job (generated)" id="1367517581199-118">
        <addForeignKeyConstraint baseColumnNames="village_id" baseTableName="users" constraintName="FK6A68E08C5AE0DB9" deferrable="false" initiallyDeferred="false" referencedColumnNames="id" referencedTableName="village"/>
    </changeSet>
    <changeSet author="Job (generated)" id="1367517581199-119">
        <addForeignKeyConstraint baseColumnNames="parish_id" baseTableName="village" constraintName="FK1B70A4AC8CDA553B" deferrable="false" initiallyDeferred="false" referencedColumnNames="id" referencedTableName="parish"/>
    </changeSet>
    <changeSet author="Job (generated)" id="1367517581199-120">
        <dropForeignKeyConstraint baseTableName="comment" constraintName="FK38A5EE5F5D1B0A9B"/>
    </changeSet>
    <changeSet author="Job (generated)" id="1367517581199-121">
        <dropForeignKeyConstraint baseTableName="committee_member" constraintName="FK1792999C3406EC59"/>
    </changeSet>
    <changeSet author="Job (generated)" id="1367517581199-122">
        <dropForeignKeyConstraint baseTableName="concept_category_link" constraintName="FKD1B211043100D8AA"/>
    </changeSet>
    <changeSet author="Job (generated)" id="1367517581199-123">
        <dropForeignKeyConstraint baseTableName="financial_service_doc" constraintName="FK3C84CDF857444DA7"/>
    </changeSet>
    <changeSet author="Job (generated)" id="1367517581199-124">
        <dropForeignKeyConstraint baseTableName="price" constraintName="FK65FB149B248849B"/>
    </changeSet>
    <changeSet author="Job (generated)" id="1367517581199-125">
        <dropForeignKeyConstraint baseTableName="price" constraintName="FK65FB149D7199ADA"/>
    </changeSet>
    <changeSet author="Job (generated)" id="1367517581199-126">
        <dropForeignKeyConstraint baseTableName="publication_documents" constraintName="FKC1E62865FADC9C3B"/>
    </changeSet>
    <changeSet author="Job (generated)" id="1367517581199-127">
        <dropForeignKeyConstraint baseTableName="publication_documents" constraintName="FKC1E628656B3B4639"/>
    </changeSet>
    <changeSet author="Job (generated)" id="1367517581199-128">
        <dropForeignKeyConstraint baseTableName="publications" constraintName="FK37B8A3C796BC074C"/>
    </changeSet>
    <changeSet author="Job (generated)" id="1367517581199-129">
        <dropForeignKeyConstraint baseTableName="role_permissions" constraintName="FKEAD9D23B140A5B7B"/>
    </changeSet>
    <changeSet author="Job (generated)" id="1367517581199-130">
        <dropForeignKeyConstraint baseTableName="role_users" constraintName="FK6CF7C0FFC67EF2DB"/>
    </changeSet>
    <changeSet author="Job (generated)" id="1367517581199-131">
        <dropForeignKeyConstraint baseTableName="staff_member" constraintName="FK5470C8D95BA33ADC"/>
    </changeSet>
    <changeSet author="Job (generated)" id="1367517581199-132">
        <dropForeignKeyConstraint baseTableName="staff_member" constraintName="FK5470C8D96BA9B6BB"/>
    </changeSet>
    <changeSet author="Job (generated)" id="1367517581199-133">
        <dropForeignKeyConstraint baseTableName="users" constraintName="FK6A68E08A1DA35B"/>
    </changeSet>
    <changeSet author="Job (generated)" id="1367517581199-134">
        <dropForeignKeyConstraint baseTableName="users" constraintName="FK6A68E082AC304E7"/>
    </changeSet>
    <changeSet author="Job (generated)" id="1367517581199-135">
        <dropForeignKeyConstraint baseTableName="users" constraintName="FK6A68E087EF2A060"/>
    </changeSet>
    <changeSet author="Job (generated)" id="1367517581199-136">
        <dropForeignKeyConstraint baseTableName="users" constraintName="FK6A68E08A3C8C159"/>
    </changeSet>
    <changeSet author="Job (generated)" id="1367517581199-137">
        <dropForeignKeyConstraint baseTableName="users" constraintName="FK6A68E08C5AE0DB9"/>
    </changeSet>
    <changeSet author="Job (generated)" id="1367517581199-138">
        <dropForeignKeyConstraint baseTableName="village" constraintName="FK1B70A4AC8CDA553B"/>
    </changeSet>
</databaseChangeLog>
